nextcloud_cookbook_api/__init__.py
nextcloud_cookbook_api/client.py
nextcloud_cookbook_api/models/__init__.py
nextcloud_cookbook_api/models/category.py
nextcloud_cookbook_api/models/config.py
nextcloud_cookbook_api/models/keyword.py
nextcloud_cookbook_api/models/recipe.py
tests/models/__init__.py
tests/models/test_category_model.py
tests/models/test_config_model.py
tests/models/test_keyword_model.py
tests/models/test_nutrition_model.py
tests/models/test_recipe_model.py
tests/models/test_recipe_stub_model.py
tests/models/test_visible_info_blocks_model.py
nextcloud_cookbook_api-0.1.0.dist-info/METADATA
nextcloud_cookbook_api-0.1.0.dist-info/WHEEL
nextcloud_cookbook_api-0.1.0.dist-info/top_level.txt
nextcloud_cookbook_api-0.1.0.dist-info/RECORD
