Metadata-Version: 2.4
Name: nextcloud_cookbook_api
Version: 0.1.0
Summary: Python API client for nextcloud cookbook app API
Home-page: https://github.com/infinityofspace/nextcloud_cookbook_api
Author: infinityofspace
License: MIT
Classifier: Development Status :: 5 - Production/Stable
Classifier: Programming Language :: Python :: 3
Classifier: Programming Language :: Python :: 3.10
Classifier: Programming Language :: Python :: 3.11
Classifier: Programming Language :: Python :: 3.12
Classifier: Programming Language :: Python :: 3.13
Classifier: Programming Language :: Python :: 3.14
Classifier: License :: OSI Approved :: MIT License
Classifier: Topic :: Internet :: WWW/HTTP
Classifier: Topic :: Utilities
Requires-Python: >=3.10
Requires-Dist: requests<3.0,>=2.0
Requires-Dist: pydantic<3.0,>=2.0
Requires-Dist: setuptools>=41.6.0
Dynamic: author
Dynamic: classifier
Dynamic: description
Dynamic: description-content-type
Dynamic: home-page
Dynamic: license
Dynamic: requires-dist
Dynamic: requires-python
Dynamic: summary
